bitspec.py
bitspec-0.4.4.dist-info/WHEEL
bitspec-0.4.4.dist-info/METADATA
bitspec-0.4.4.dist-info/RECORD
