Metadata-Version: 2.1
Name: bitspec
Version: 0.4.4
Summary: Bit pattern mini-language for instruction encodings. Bytes in, IR out!
Author: amtal
Requires-Python: >=3.8
Classifier: Topic :: Software Development :: Disassemblers
Classifier: License :: OSI Approved :: MIT License
Project-URL: Documentation, https://amtal.github.io/bitspec
Project-URL: Issues, https://github.com/amtal/bitspec/issues
Project-URL: Source, https://github.com/amtal/bitspec
